ABTesting/__init__.py
ABTesting/controller.py
ABTesting/utils.py
py_ab_testing-1.3.1.dist-info/METADATA
py_ab_testing-1.3.1.dist-info/WHEEL
py_ab_testing-1.3.1.dist-info/top_level.txt
py_ab_testing-1.3.1.dist-info/RECORD
